[
	{
		"name": "Instagram Comments Scrapper",
		"image": "project-1.png",
		"url": "https://telegram.me/iamprcompanybot",
		"date": "Aug 2016",
		"tags": ["Telegram Bot","Ruby"]
	},
	{
		"name": "Youtube \\ Instagram Video Downloader",
		"image": "project-2.png",
		"url": "https://telegram.me/instatube_bot",
		"date": "Aug 2016",
		"tags": ["Telegram Bot","Ruby"]
	},
	{
		"name": "Image Cropper (Instagram Grid)",
		"image": "project-3.png",
		"url": "https://telegram.me/LandingPageInstagramBot",
		"date": "Aug 2016",
		"tags": ["Telegram Bot","Ruby"]
	},
	{
		"name": "Simple Site For Event Organizer",
		"image": "project-4.png",
		"url": "http://prazdnikinaura.ru/",
		"date": "Oct 2015",
		"tags": ["PHP","CodeIgniter", "VK API"]
	}
]